{
  "file": "./src/bin/patina-index.rs",
  "language": "rust",
  "functions": [
    {
      "name": "main",
      "visibility": "public",
      "async": false,
      "unsafe": false,
      "params": [],
      "returns": null,
      "line_start": 31,
      "line_end": 131,
      "doc_comment": null
    },
    {
      "name": "get_cache_path",
      "visibility": "public",
      "async": false,
      "unsafe": false,
      "params": [],
      "returns": null,
      "line_start": 134,
      "line_end": 140,
      "doc_comment": null
    },
    {
      "name": "should_skip_parse",
      "visibility": "public",
      "async": false,
      "unsafe": false,
      "params": [],
      "returns": null,
      "line_start": 142,
      "line_end": 151,
      "doc_comment": null
    }
  ],
  "types": [
    {
      "name": "Args",
      "kind": "struct",
      "visibility": "public",
      "fields": [],
      "methods": [],
      "line_start": 9,
      "line_end": 29,
      "doc_comment": null
    }
  ],
  "imports": [
    {
      "path": "anyhow::{Context, Result}",
      "items": [],
      "alias": null,
      "line": 1
    },
    {
      "path": "clap::Parser",
      "items": [],
      "alias": null,
      "line": 2
    },
    {
      "path": "patina::pipeline::{analyze_git, detect_language, discover_files, generate_sql, load_into_duckdb, parse_file}",
      "items": [],
      "alias": null,
      "line": 3
    },
    {
      "path": "std::path::{Path, PathBuf}",
      "items": [],
      "alias": null,
      "line": 4
    }
  ],
  "calls": [
    {
      "target": "Args::parse",
      "caller": "main",
      "line": 32,
      "is_method": false,
      "is_async": false
    },
    {
      "target": "with_context",
      "caller": "main",
      "line": 35,
      "is_method": true,
      "is_async": false
    },
    {
      "target": "std::fs::create_dir_all",
      "caller": "main",
      "line": 35,
      "is_method": false,
      "is_async": false
    },
    {
      "target": "format!",
      "caller": "main",
      "line": 36,
      "is_method": false,
      "is_async": false
    },
    {
      "target": "join",
      "caller": "main",
      "line": 39,
      "is_method": true,
      "is_async": false
    },
    {
      "target": "std::fs::create_dir_all",
      "caller": "main",
      "line": 40,
      "is_method": false,
      "is_async": false
    },
    {
      "target": "println!",
      "caller": "main",
      "line": 42,
      "is_method": false,
      "is_async": false
    },
    {
      "target": "println!",
      "caller": "main",
      "line": 43,
      "is_method": false,
      "is_async": false
    },
    {
      "target": "println!",
      "caller": "main",
      "line": 47,
      "is_method": false,
      "is_async": false
    },
    {
      "target": "discover_files",
      "caller": "main",
      "line": 50,
      "is_method": false,
      "is_async": false
    },
    {
      "target": "analyze_git",
      "caller": "main",
      "line": 51,
      "is_method": false,
      "is_async": false
    },
    {
      "target": "println!",
      "caller": "main",
      "line": 53,
      "is_method": false,
      "is_async": false
    },
    {
      "target": "join",
      "caller": "main",
      "line": 56,
      "is_method": true,
      "is_async": false
    },
    {
      "target": "std::fs::write",
      "caller": "main",
      "line": 57,
      "is_method": false,
      "is_async": false
    },
    {
      "target": "serde_json::to_string_pretty",
      "caller": "main",
      "line": 59,
      "is_method": false,
      "is_async": false
    },
    {
      "target": "println!",
      "caller": "main",
      "line": 64,
      "is_method": false,
      "is_async": false
    },
    {
      "target": "get_cache_path",
      "caller": "main",
      "line": 71,
      "is_method": false,
      "is_async": false
    },
    {
      "target": "should_skip_parse",
      "caller": "main",
      "line": 74,
      "is_method": false,
      "is_async": false
    },
    {
      "target": "println!",
      "caller": "main",
      "line": 76,
      "is_method": false,
      "is_async": false
    },
    {
      "target": "println!",
      "caller": "main",
      "line": 83,
      "is_method": false,
      "is_async": false
    },
    {
      "target": "parse_file",
      "caller": "main",
      "line": 87,
      "is_method": false,
      "is_async": false
    },
    {
      "target": "parent",
      "caller": "main",
      "line": 90,
      "is_method": true,
      "is_async": false
    },
    {
      "target": "std::fs::create_dir_all",
      "caller": "main",
      "line": 91,
      "is_method": false,
      "is_async": false
    },
    {
      "target": "std::fs::write",
      "caller": "main",
      "line": 95,
      "is_method": false,
      "is_async": false
    },
    {
      "target": "serde_json::to_string_pretty",
      "caller": "main",
      "line": 97,
      "is_method": false,
      "is_async": false
    },
    {
      "target": "println!",
      "caller": "main",
      "line": 103,
      "is_method": false,
      "is_async": false
    },
    {
      "target": "println!",
      "caller": "main",
      "line": 106,
      "is_method": false,
      "is_async": false
    },
    {
      "target": "Ok",
      "caller": "main",
      "line": 107,
      "is_method": false,
      "is_async": false
    },
    {
      "target": "println!",
      "caller": "main",
      "line": 112,
      "is_method": false,
      "is_async": false
    },
    {
      "target": "join",
      "caller": "main",
      "line": 115,
      "is_method": true,
      "is_async": false
    },
    {
      "target": "generate_sql",
      "caller": "main",
      "line": 116,
      "is_method": false,
      "is_async": false
    },
    {
      "target": "println!",
      "caller": "main",
      "line": 118,
      "is_method": false,
      "is_async": false
    },
    {
      "target": "println!",
      "caller": "main",
      "line": 122,
      "is_method": false,
      "is_async": false
    },
    {
      "target": "join",
      "caller": "main",
      "line": 125,
      "is_method": true,
      "is_async": false
    },
    {
      "target": "load_into_duckdb",
      "caller": "main",
      "line": 126,
      "is_method": false,
      "is_async": false
    },
    {
      "target": "println!",
      "caller": "main",
      "line": 128,
      "is_method": false,
      "is_async": false
    },
    {
      "target": "Ok",
      "caller": "main",
      "line": 130,
      "is_method": false,
      "is_async": false
    },
    {
      "target": "unwrap_or",
      "caller": "get_cache_path",
      "line": 135,
      "is_method": true,
      "is_async": false
    },
    {
      "target": "strip_prefix",
      "caller": "get_cache_path",
      "line": 135,
      "is_method": true,
      "is_async": false
    },
    {
      "target": "join",
      "caller": "get_cache_path",
      "line": 136,
      "is_method": true,
      "is_async": false
    },
    {
      "target": "format!",
      "caller": "get_cache_path",
      "line": 137,
      "is_method": false,
      "is_async": false
    },
    {
      "target": "set_extension",
      "caller": "get_cache_path",
      "line": 138,
      "is_method": true,
      "is_async": false
    },
    {
      "target": "exists",
      "caller": "should_skip_parse",
      "line": 143,
      "is_method": true,
      "is_async": false
    },
    {
      "target": "Ok",
      "caller": "should_skip_parse",
      "line": 144,
      "is_method": false,
      "is_async": false
    },
    {
      "target": "modified",
      "caller": "should_skip_parse",
      "line": 147,
      "is_method": true,
      "is_async": false
    },
    {
      "target": "std::fs::metadata",
      "caller": "should_skip_parse",
      "line": 147,
      "is_method": false,
      "is_async": false
    },
    {
      "target": "modified",
      "caller": "should_skip_parse",
      "line": 148,
      "is_method": true,
      "is_async": false
    },
    {
      "target": "std::fs::metadata",
      "caller": "should_skip_parse",
      "line": 148,
      "is_method": false,
      "is_async": false
    },
    {
      "target": "Ok",
      "caller": "should_skip_parse",
      "line": 150,
      "is_method": false,
      "is_async": false
    }
  ]
}